giveagame/Coords.py
giveagame/GUI.py
giveagame/Game.py
giveagame/Music.py
giveagame/__init__.py
giveagame/sprites/DoorSprite.py
giveagame/sprites/MovingPlatformSprite.py
giveagame/sprites/PlatformSprite.py
giveagame/sprites/Sprite.py
giveagame/sprites/StickFigureSprite.py
giveagame/sprites/__init__.py
giveagame-0.0.11.dist-info/LICENSE
giveagame-0.0.11.dist-info/METADATA
giveagame-0.0.11.dist-info/WHEEL
giveagame-0.0.11.dist-info/top_level.txt
giveagame-0.0.11.dist-info/RECORD
