Metadata-Version: 2.1
Name: giveagame
Version: 0.0.11
Summary: A simple game engine...
Home-page: https://www.github.com/misha-network/giveagame/
Author: misha-network
Author-email: misha.network.email@gmail.com
Project-URL: Bug Tracker, https://www.github.com/misha-network/giveagame/issues/
Classifier: Programming Language :: Python :: 3
Classifier: License :: OSI Approved :: GNU General Public License v3 (GPLv3)
Classifier: Operating System :: OS Independent
Requires-Python: >=3.10
License-File: LICENSE
